Metadata-Version: 2.1
Name: odoo-addon-stock_storage_type_putaway_abc
Version: 18.0.1.0.1
Requires-Python: >=3.10
Requires-Dist: odoo-addon-stock_storage_type==18.0.*
Requires-Dist: odoo==18.0.*
Summary: Advanced storage strategy ABC for WMS
Home-page: https://github.com/OCA/stock-logistics-putaway
License: AGPL-3
Author: Camptocamp, BCIM, Odoo Community Association (OCA)
Author-email: support@odoo-community.org
Classifier: Programming Language :: Python
Classifier: Framework :: Odoo
Classifier: Framework :: Odoo :: 18.0
Classifier: License :: OSI Approved :: GNU Affero General Public License v3
